[{"form_number": "Form W-2", "form_title": "Wage and Tax Statement (Info Copy Only)", "year": 2017}, {"form_number": "Form W-2", "form_title": "Wage and Tax Statement (Info Copy Only)", "year": 1992}, {"form_number": "Form W-2", "form_title": "Wage and Tax Statement (Info Copy Only)", "year": 1965}, {"form_number": "Form W-2AS", "form_title": "American Samoa Wage and Tax Statement (Info Copy Only)", "year": 2008}, {"form_number": "Form W-2C", "form_title": "Corrected Wage and Tax Statement (Info Copy Only)", "year": 1997}, {"form_number": "Form W-2G", "form_title": "Certain Gambling Winnings", "year": 2004}, {"form_number": "Form W-2GU", "form_title": "Guam Wage and Tax Statement (Info Copy Only)", "year": 2011}, {"form_number": "Form W-2VI", "form_title": "U.S. Virgin Islands Wage and Tax Statement (Info Copy Only)", "year": 2018}, {"form_number": "Form W-2VI", "form_title": "U.S. Virgin Islands Wage and Tax Statement (Info Copy Only)", "year": 1992}, {"form_number": "Form W-2VI", "form_title": "U.S. Virgin Islands Wage and Tax Statement (Info Copy Only)", "year": 1990}]